tastyerrors/__init__.py
tastyerrors-2025.0.2.dist-info/licenses/license.txt
tastyerrors-2025.0.2.dist-info/METADATA
tastyerrors-2025.0.2.dist-info/WHEEL
tastyerrors-2025.0.2.dist-info/top_level.txt
tastyerrors-2025.0.2.dist-info/RECORD
