Metadata-Version: 2.4
Name: tastyerrors
Version: 2025.0.2
Summary: An awesome library for  40+ additional useful Python exceptions
Author: Arjun Singh
Author-email: arjunpride15@gmail.com
License: Apache License 2.0
Classifier: Programming Language :: Python :: 3
Classifier: License :: OSI Approved :: Apache Software License
Classifier: Operating System :: OS Independent
License-File: license.txt
Dynamic: author
Dynamic: author-email
Dynamic: classifier
Dynamic: description
Dynamic: description-content-type
Dynamic: license
Dynamic: license-file
Dynamic: summary
